Metadata-Version: 1.0
Name: Bigauss-probability-distribution
Version: 0.1
Summary: Binomial and Gaussian distributions
Home-page: UNKNOWN
Author: Abhishek Chaturvedi
Author-email: UNKNOWN
License: UNKNOWN
Platform: UNKNOWN
